xdynamo/__init__.py
xdynamo/api.py
xdynamo/client.py
xdynamo/common_types.py
xdynamo/const.py
xdynamo/db.py
xdynamo/errors.py
xdynamo/fields.py
xdynamo/meta.json
xdynamo/model.py
xdynamo/resources.py
xdynamo/structure.py
xdynamo/utils.py
xdynamo-0.10.0.dist-info/METADATA
xdynamo-0.10.0.dist-info/WHEEL
xdynamo-0.10.0.dist-info/RECORD
